setup.cfg
setup.py
python_slimta_diskstorage.egg-info/PKG-INFO
python_slimta_diskstorage.egg-info/SOURCES.txt
python_slimta_diskstorage.egg-info/dependency_links.txt
python_slimta_diskstorage.egg-info/namespace_packages.txt
python_slimta_diskstorage.egg-info/requires.txt
python_slimta_diskstorage.egg-info/top_level.txt
slimta/__init__.py
slimta/diskstorage/__init__.py
test/test_slimta_queue_disk.py